{
    "os": "Linux-4.15.0-208-generic-x86_64-with-glibc2.27",
    "python": "3.10.10",
    "heartbeatAt": "2023-04-07T21:07:45.265178",
    "startedAt": "2023-04-07T21:07:44.698096",
    "docker": null,
    "cuda": null,
    "args": null,
    "state": "running",
    "program": "<python with no main file>",
    "git": {
        "remote": "https://github.com/EvanSamaa/Gaze_project.git",
        "commit": "13c289dfdf5325e8b8c5c1bbebdb2b64917c9b6c"
    },
    "email": "evan12345pan@hotmail.com",
    "root": "/nfs/artemis.dgpsrv/ondemand27/evanpan/Gaze_project",
    "host": "jason",
    "username": "evanpan",
    "executable": "/scratch/ondemand27/evanpan/conda_env/.conda/envs/jaligaze/bin/python",
    "cpu_count": 28,
    "cpu_count_logical": 28,
    "cpu_freq": {
        "current": 1830.991357142857,
        "min": 0.0,
        "max": 0.0
    },
    "cpu_freq_per_core": [
        {
            "current": 2623.085,
            "min": 0.0,
            "max": 0.0
        },
        {
            "current": 1128.098,
            "min": 0.0,
            "max": 0.0
        },
        {
            "current": 2913.126,
            "min": 0.0,
            "max": 0.0
        },
        {
            "current": 1286.635,
            "min": 0.0,
            "max": 0.0
        },
        {
            "current": 1246.748,
            "min": 0.0,
            "max": 0.0
        },
        {
            "current": 1285.861,
            "min": 0.0,
            "max": 0.0
        },
        {
            "current": 2264.295,
            "min": 0.0,
            "max": 0.0
        },
        {
            "current": 1271.15,
            "min": 0.0,
            "max": 0.0
        },
        {
            "current": 1547.381,
            "min": 0.0,
            "max": 0.0
        },
        {
            "current": 1274.599,
            "min": 0.0,
            "max": 0.0
        },
        {
            "current": 2875.985,
            "min": 0.0,
            "max": 0.0
        },
        {
            "current": 1966.127,
            "min": 0.0,
            "max": 0.0
        },
        {
            "current": 2275.942,
            "min": 0.0,
            "max": 0.0
        },
        {
            "current": 1461.373,
            "min": 0.0,
            "max": 0.0
        },
        {
            "current": 2270.913,
            "min": 0.0,
            "max": 0.0
        },
        {
            "current": 1971.679,
            "min": 0.0,
            "max": 0.0
        },
        {
            "current": 1503.287,
            "min": 0.0,
            "max": 0.0
        },
        {
            "current": 1467.304,
            "min": 0.0,
            "max": 0.0
        },
        {
            "current": 2311.035,
            "min": 0.0,
            "max": 0.0
        },
        {
            "current": 1975.67,
            "min": 0.0,
            "max": 0.0
        },
        {
            "current": 2446.733,
            "min": 0.0,
            "max": 0.0
        },
        {
            "current": 1328.88,
            "min": 0.0,
            "max": 0.0
        },
        {
            "current": 2306.493,
            "min": 0.0,
            "max": 0.0
        },
        {
            "current": 1961.088,
            "min": 0.0,
            "max": 0.0
        },
        {
            "current": 2316.111,
            "min": 0.0,
            "max": 0.0
        },
        {
            "current": 1156.643,
            "min": 0.0,
            "max": 0.0
        },
        {
            "current": 1763.626,
            "min": 0.0,
            "max": 0.0
        },
        {
            "current": 1067.891,
            "min": 0.0,
            "max": 0.0
        }
    ],
    "disk": {
        "total": 937.3305015563965,
        "used": 50.05482482910156
    },
    "gpu": "TITAN RTX",
    "gpu_count": 2,
    "gpu_devices": [
        {
            "name": "TITAN RTX",
            "memory_total": 25396838400
        },
        {
            "name": "TITAN RTX",
            "memory_total": 25396838400
        }
    ],
    "memory": {
        "total": 376.5566101074219
    }
}
